igdb/__init__.py
igdb/igdbapi_pb2.py
igdb/wrapper.py
igdb_api_v4-0.3.3.dist-info/LICENSE
igdb_api_v4-0.3.3.dist-info/METADATA
igdb_api_v4-0.3.3.dist-info/WHEEL
igdb_api_v4-0.3.3.dist-info/top_level.txt
igdb_api_v4-0.3.3.dist-info/RECORD
