Metadata-Version: 2.1
Name: igdb-api-v4
Version: 0.3.3
Summary: An API wrapper for IGDB API v4
Home-page: https://github.com/twitchtv/igdb-api-python/
Author: IGDB
Author-email: dev@igdb.com
Classifier: Programming Language :: Python :: 3
Classifier: License :: OSI Approved :: MIT License
Classifier: Operating System :: OS Independent
Requires-Python: >=3
License-File: LICENSE
